shell_osc/__init__.py
shell_osc/__main__.py
shell_osc/client.py
shell_osc/server.py
shell_osc-0.1.0a0.dist-info/LICENSE
shell_osc-0.1.0a0.dist-info/METADATA
shell_osc-0.1.0a0.dist-info/WHEEL
shell_osc-0.1.0a0.dist-info/entry_points.txt
shell_osc-0.1.0a0.dist-info/top_level.txt
shell_osc-0.1.0a0.dist-info/RECORD
